pyzenkit/__init__.py
pyzenkit/baseapp.py
pyzenkit/daemonizer.py
pyzenkit/jsonconf.py
pyzenkit/utils.py
pyzenkit/zencli.py
pyzenkit/zendaemon.py
pyzenkit/zenscript.py
pyzenkit/tests/__init__.py
pyzenkit/tests/test_baseapp.py
pyzenkit/tests/test_daemonizer.py
pyzenkit/tests/test_jsonconf.py
pyzenkit/tests/test_zendaemon.py
pyzenkit/tests/test_zenscript.py
pyzenkit/zencli_modules/__init__.py
pyzenkit/zencli_modules/another_demo_module.py
pyzenkit/zencli_modules/demo_module.py
pyzenkit-0.66.dist-info/licenses/LICENSE.txt
pyzenkit-0.66.dist-info/METADATA
pyzenkit-0.66.dist-info/WHEEL
pyzenkit-0.66.dist-info/top_level.txt
pyzenkit-0.66.dist-info/RECORD
