Metadata-Version: 2.4
Name: pyzenkit
Version: 0.66
Summary: Python 3 script and daemon toolkit
Home-page: https://pypi.org/project/pyzenkit/
Author: Honza Mach
Author-email: honza.mach.ml@gmail.com
License: MIT
Project-URL: Documentation, https://709.gitlab-pages.cesnet.cz/mentat/pyzenkit/master/html/manual.html
Project-URL: Source, https://gitlab.cesnet.cz/709/mentat/pyzenkit
Project-URL: Tracker, https://gitlab.cesnet.cz/709/mentat/pyzenkit/-/issues
Keywords: library console script daemon
Classifier: Development Status :: 3 - Alpha
Classifier: License :: OSI Approved :: MIT License
Classifier: Programming Language :: Python :: 3 :: Only
Classifier: Environment :: Console
License-File: LICENSE.txt
Requires-Dist: python-dotenv
Requires-Dist: jsonschema
Requires-Dist: pydgets
Dynamic: author
Dynamic: author-email
Dynamic: classifier
Dynamic: description
Dynamic: home-page
Dynamic: keywords
Dynamic: license
Dynamic: license-file
Dynamic: project-url
Dynamic: requires-dist
Dynamic: summary
